README.rst
setup.py
organization_chart_of_inpe/__init__.py
organization_chart_of_inpe/constants.py
organization_chart_of_inpe.egg-info/PKG-INFO
organization_chart_of_inpe.egg-info/SOURCES.txt
organization_chart_of_inpe.egg-info/dependency_links.txt
organization_chart_of_inpe.egg-info/top_level.txt