Metadata-Version: 1.1
Name: organization-chart-of-inpe
Version: 1.0.3
Summary: Organization Chart Of INPE
Home-page: UNKNOWN
Author: Rodrigo M. Mariano
Author-email: rodrigo.rmm@live.com
License: MIT
Platform: UNKNOWN
Classifier: Development Status :: 3 - Alpha
Classifier: Intended Audience :: Developers
Classifier: Topic :: Software Development :: Build Tools
Classifier: License :: OSI Approved :: MIT License
Classifier: Programming Language :: Python :: 3
